sumpy/__init__.py
sumpy/proto/__init__.py
sumpy/proto/sum_pb2.py
sumpy/proto/sum_pb2_grpc.py
sum_py-1.3.4.dist-info/LICENSE.md
sum_py-1.3.4.dist-info/METADATA
sum_py-1.3.4.dist-info/WHEEL
sum_py-1.3.4.dist-info/top_level.txt
sum_py-1.3.4.dist-info/RECORD
