Metadata-Version: 2.1
Name: sum-py
Version: 1.3.4
Summary: Python client for Sum linear algebra database.
Home-page: http://www.github.com/evilsocket/sumpy
Author: Simone Margaritelli
Author-email: evilsocket@gmail.com
License: GPL3
Platform: UNKNOWN
Classifier: Development Status :: 5 - Production/Stable
Classifier: Environment :: Console
Classifier: Intended Audience :: Developers
Classifier: License :: OSI Approved :: GNU General Public License (GPL)
Classifier: Operating System :: OS Independent
Classifier: Programming Language :: Python
Classifier: Programming Language :: Python :: 3
Requires-Python: >=3.0
